{
    "type": "minecraft:crafting_shaped",
    "pattern": [
        " x ",
        "xyx",
        " x "
    ],
    "key": {
        "x": {
            "type": "forge:ore_dict",
            "ore": "string"
        },
        "y": [
            {
				"item": "ebwizardry:magic_crystal",
				"data": 0
			},
			{
				"item": "ebwizardry:magic_crystal",
				"data": 1
			},
			{
				"item": "ebwizardry:magic_crystal",
				"data": 2
			},
			{
				"item": "ebwizardry:magic_crystal",
				"data": 3
			},
			{
				"item": "ebwizardry:magic_crystal",
				"data": 4
			},
			{
				"item": "ebwizardry:magic_crystal",
				"data": 5
			},
			{
				"item": "ebwizardry:magic_crystal",
				"data": 6
			},
			{
				"item": "ebwizardry:magic_crystal",
				"data": 7
			}
        ]
    },
    "result": {
        "item": "ebwizardry:magic_silk",
        "count": 2
    }
}
